pybimfile/__init__.py
pybimfile/bimfile.py
pybimfile-0.0.1.dist-info/LICENSE.md
pybimfile-0.0.1.dist-info/METADATA
pybimfile-0.0.1.dist-info/WHEEL
pybimfile-0.0.1.dist-info/top_level.txt
pybimfile-0.0.1.dist-info/RECORD
