Metadata-Version: 2.1
Name: pybimfile
Version: 0.0.1
Summary: pybimfile - python implementation of a before image file (BIM File)
Home-page: https://github.com/kr-g/pybimfile
Author: k.r. goger
Author-email: k.r.goger+pybimfile@gmail.com
License: UNKNOWN
Keywords: python before image file (BIM File) copy-on-write
Platform: UNKNOWN
Classifier: Development Status :: 3 - Alpha
Classifier: Operating System :: POSIX :: Linux
Classifier: Intended Audience :: Developers
Classifier: Programming Language :: Python :: 3
Classifier: License :: OSI Approved :: GNU Affero General Public License v3 or later (AGPLv3+)
Requires-Python: >=3.6
